README.rst
setup.cfg
setup.py
muppet/__init__.py
muppet/durable_channel.py
muppet/remote_channel.py
muppet.egg-info/PKG-INFO
muppet.egg-info/SOURCES.txt
muppet.egg-info/dependency_links.txt
muppet.egg-info/requires.txt
muppet.egg-info/top_level.txt
test/test_durable_channel.py
test/test_remote_channel.py