Metadata-Version: 1.0
Name: muppet
Version: 0.1.6
Summary: Durable messaging for distributed processing
Home-page: https://github.com/pandastrike/muppet
Author: Daniel Yoder, Mahesh Yellai
Author-email: daniel.yoder@gmail.com, mahesh.yellai@gmail.com
License: MIT
Keywords: Durable messaging,Distributed processing,Redis
Platform: UNKNOWN
